polarpy/__init__.py
polarpy/callbacks.py
polarpy/commands.py
polarpy/constants.py
polarpy/device.py
polarpy/header_parser.py
polarpy/headers.py
polarpy/measurement_parser.py
polarpy/measurement_settings_parser.py
polarpy/parser.py
polarpy/settings.py
polarpy/stream_reader.py
polarpy-0.1.1.dist-info/METADATA
polarpy-0.1.1.dist-info/WHEEL
polarpy-0.1.1.dist-info/RECORD
