Metadata-Version: 2.1
Name: polarpy
Version: 0.1.1
Summary: Tools for reading and fusing live data streams from Polar OH1 (PPG) and H10 (ECG) sensors.
Home-page: https://github.com/wideopensource/polarpy
License: MIT
Author: wideopentech
Author-email: fossie@wideoppentech.co.uk
Requires-Python: >=3.8,<4.0
Classifier: License :: OSI Approved :: MIT License
Classifier: Operating System :: POSIX :: Linux
Classifier: Programming Language :: Python :: 3
Classifier: Programming Language :: Python :: 3.8
Classifier: Programming Language :: Python :: 3.9
Classifier: Programming Language :: Python :: 3.10
Classifier: Programming Language :: Python :: 3.11
Classifier: Programming Language :: Python :: 3
Requires-Dist: pygatttool (>=0.1.1a3,<0.2.0)
Project-URL: Repository, https://github.com/wideopensource/polarpy
